<?xml version="1.0" encoding="utf-8"?>
<savedqueries>
  <savedquery>
    <IsCustomizable>1</IsCustomizable>
    <CanBeDeleted>0</CanBeDeleted>
    <isquickfindquery>1</isquickfindquery>
    <isprivate>0</isprivate>
    <isdefault>1</isdefault>
    <savedqueryid>{eb94c9e9-baa0-47e5-8980-92e0d35655df}</savedqueryid>
    <layoutxml>
      <grid name="resultset" jump="gsscore_name" select="1" icon="1" preview="1">
        <row name="result" id="gsscore_materialindexid">
          <cell name="gsscore_name" width="300" />
        </row>
      </grid>
    </layoutxml>
    <querytype>4</querytype>
    <fetchxml>
      <fetch version="1.0" mapping="logical">
        <entity name="gsscore_materialindex">
          <attribute name="gsscore_materialindexid" />
          <attribute name="gsscore_name" />
        </entity>
      </fetch>
    </fetchxml>
    <IntroducedVersion>1.0.0.126</IntroducedVersion>
    <LocalizedNames>
      <LocalizedName description="Quick Find Active Material Indexes" languagecode="1033" />
    </LocalizedNames>
  </savedquery>
</savedqueries>